colored_python/__init__.py
colored_python/colored.py
colored_python-1.2.1.dist-info/LICENSE
colored_python-1.2.1.dist-info/METADATA
colored_python-1.2.1.dist-info/WHEEL
colored_python-1.2.1.dist-info/top_level.txt
colored_python-1.2.1.dist-info/RECORD
