Metadata-Version: 2.1
Name: colored-python
Version: 1.2.1
Summary: A lightweight python module to print colored text to the terminal easily
Home-page: https://github.com/just-a-mango/coloredpython
Author: Just_a_Mango
Author-email: justamango@altmails.com
Project-URL: Bug Tracker, https://github.com/just-a-mango/coloredpython/issues
Classifier: Programming Language :: Python :: 3
Classifier: License :: OSI Approved :: MIT License
Classifier: Operating System :: OS Independent
Requires-Python: >=3.6
License-File: LICENSE
